{
  "campeonato": "6ª COPA SICREDI LIVRE MASCULINO",
  "rodada_atual": 10,
  "rodadas": [
    {
      "nome": "Rodada 10 de 10",
      "jogos": [
        {
          "mandante": "E.C RONDOFRIO",
          "visitante": "R.C SPORTS",
          "gols_mandante": 4,
          "gols_visitante": 2,
          "campo": "ARENA PRIME SOCIETY",
          "data_hora": "29/04/2026 20:30"
        },
        {
          "mandante": "GG PINTURAS/SANTA MARIA",
          "visitante": "SHALON FC",
          "gols_mandante": 3,
          "gols_visitante": 5,
          "campo": "ARENA PRIME SOCIETY",
          "data_hora": "29/04/2026 21:30"
        },
        {
          "mandante": "SEDE DO GORDO",
          "visitante": "MECANICA CASTELI / HORTIAGRO F.C",
          "gols_mandante": 2,
          "gols_visitante": 3,
          "campo": "GUATAMBU SOCIETY",
          "data_hora": "30/04/2026 20:00"
        },
        {
          "mandante": "LJS/P2",
          "visitante": "BOLEIROS/MDM CONSTRUÇÕES E PINTURAS",
          "gols_mandante": 5,
          "gols_visitante": 5,
          "campo": "GUATAMBU SOCIETY",
          "data_hora": "30/04/2026 21:00"
        },
        {
          "mandante": "LJS/P2",
          "visitante": "BOLEIROS/MDM CONSTRUÇÕES E PINTURAS",
          "gols_mandante": 7,
          "gols_visitante": 6,
          "campo": "Pênalti",
          "data_hora": "30/04/2026 21:30"
        },
        {
          "mandante": "SHALON FC",
          "visitante": "LJS/P2",
          "gols_mandante": null,
          "gols_visitante": null,
          "campo": "ARENA PRIME SOCIETY",
          "data_hora": "13/05/2026 20:30"
        },
        {
          "mandante": "E.C RONDOFRIO",
          "visitante": "MECANICA CASTELI / HORTIAGRO F.C",
          "gols_mandante": null,
          "gols_visitante": null,
          "campo": "ARENA PRIME SOCIETY",
          "data_hora": "13/05/2026 21:30"
        }
      ]
    },
    {
      "nome": "Rodada 10 de 10",
      "jogos": [
        {
          "mandante": "E.C RONDOFRIO",
          "visitante": "R.C SPORTS",
          "gols_mandante": 4,
          "gols_visitante": 2,
          "campo": "ARENA PRIME SOCIETY",
          "data_hora": "29/04/2026 20:30"
        },
        {
          "mandante": "GG PINTURAS/SANTA MARIA",
          "visitante": "SHALON FC",
          "gols_mandante": 3,
          "gols_visitante": 5,
          "campo": "ARENA PRIME SOCIETY",
          "data_hora": "29/04/2026 21:30"
        },
        {
          "mandante": "SEDE DO GORDO",
          "visitante": "MECANICA CASTELI / HORTIAGRO F.C",
          "gols_mandante": 2,
          "gols_visitante": 3,
          "campo": "GUATAMBU SOCIETY",
          "data_hora": "30/04/2026 20:00"
        },
        {
          "mandante": "LJS/P2",
          "visitante": "BOLEIROS/MDM CONSTRUÇÕES E PINTURAS",
          "gols_mandante": 5,
          "gols_visitante": 5,
          "campo": "GUATAMBU SOCIETY",
          "data_hora": "30/04/2026 21:00"
        },
        {
          "mandante": "LJS/P2",
          "visitante": "BOLEIROS/MDM CONSTRUÇÕES E PINTURAS",
          "gols_mandante": 7,
          "gols_visitante": 6,
          "campo": "Pênalti",
          "data_hora": "30/04/2026 21:30"
        },
        {
          "mandante": "SHALON FC",
          "visitante": "LJS/P2",
          "gols_mandante": null,
          "gols_visitante": null,
          "campo": "ARENA PRIME SOCIETY",
          "data_hora": "13/05/2026 20:30"
        },
        {
          "mandante": "E.C RONDOFRIO",
          "visitante": "MECANICA CASTELI / HORTIAGRO F.C",
          "gols_mandante": null,
          "gols_visitante": null,
          "campo": "ARENA PRIME SOCIETY",
          "data_hora": "13/05/2026 21:30"
        }
      ]
    },
    {
      "nome": "Rodada 10 de 10",
      "jogos": [
        {
          "mandante": "E.C RONDOFRIO",
          "visitante": "R.C SPORTS",
          "gols_mandante": 4,
          "gols_visitante": 2,
          "campo": "ARENA PRIME SOCIETY",
          "data_hora": "29/04/2026 20:30"
        },
        {
          "mandante": "GG PINTURAS/SANTA MARIA",
          "visitante": "SHALON FC",
          "gols_mandante": 3,
          "gols_visitante": 5,
          "campo": "ARENA PRIME SOCIETY",
          "data_hora": "29/04/2026 21:30"
        },
        {
          "mandante": "SEDE DO GORDO",
          "visitante": "MECANICA CASTELI / HORTIAGRO F.C",
          "gols_mandante": 2,
          "gols_visitante": 3,
          "campo": "GUATAMBU SOCIETY",
          "data_hora": "30/04/2026 20:00"
        },
        {
          "mandante": "LJS/P2",
          "visitante": "BOLEIROS/MDM CONSTRUÇÕES E PINTURAS",
          "gols_mandante": 5,
          "gols_visitante": 5,
          "campo": "GUATAMBU SOCIETY",
          "data_hora": "30/04/2026 21:00"
        },
        {
          "mandante": "LJS/P2",
          "visitante": "BOLEIROS/MDM CONSTRUÇÕES E PINTURAS",
          "gols_mandante": 7,
          "gols_visitante": 6,
          "campo": "Pênalti",
          "data_hora": "30/04/2026 21:30"
        },
        {
          "mandante": "SHALON FC",
          "visitante": "LJS/P2",
          "gols_mandante": null,
          "gols_visitante": null,
          "campo": "ARENA PRIME SOCIETY",
          "data_hora": "13/05/2026 20:30"
        },
        {
          "mandante": "E.C RONDOFRIO",
          "visitante": "MECANICA CASTELI / HORTIAGRO F.C",
          "gols_mandante": null,
          "gols_visitante": null,
          "campo": "ARENA PRIME SOCIETY",
          "data_hora": "13/05/2026 21:30"
        }
      ]
    },
    {
      "nome": "Rodada 10 de 10",
      "jogos": [
        {
          "mandante": "E.C RONDOFRIO",
          "visitante": "R.C SPORTS",
          "gols_mandante": 4,
          "gols_visitante": 2,
          "campo": "ARENA PRIME SOCIETY",
          "data_hora": "29/04/2026 20:30"
        },
        {
          "mandante": "GG PINTURAS/SANTA MARIA",
          "visitante": "SHALON FC",
          "gols_mandante": 3,
          "gols_visitante": 5,
          "campo": "ARENA PRIME SOCIETY",
          "data_hora": "29/04/2026 21:30"
        },
        {
          "mandante": "SEDE DO GORDO",
          "visitante": "MECANICA CASTELI / HORTIAGRO F.C",
          "gols_mandante": 2,
          "gols_visitante": 3,
          "campo": "GUATAMBU SOCIETY",
          "data_hora": "30/04/2026 20:00"
        },
        {
          "mandante": "LJS/P2",
          "visitante": "BOLEIROS/MDM CONSTRUÇÕES E PINTURAS",
          "gols_mandante": 5,
          "gols_visitante": 5,
          "campo": "GUATAMBU SOCIETY",
          "data_hora": "30/04/2026 21:00"
        },
        {
          "mandante": "LJS/P2",
          "visitante": "BOLEIROS/MDM CONSTRUÇÕES E PINTURAS",
          "gols_mandante": 7,
          "gols_visitante": 6,
          "campo": "Pênalti",
          "data_hora": "30/04/2026 21:30"
        },
        {
          "mandante": "SHALON FC",
          "visitante": "LJS/P2",
          "gols_mandante": null,
          "gols_visitante": null,
          "campo": "ARENA PRIME SOCIETY",
          "data_hora": "13/05/2026 20:30"
        },
        {
          "mandante": "E.C RONDOFRIO",
          "visitante": "MECANICA CASTELI / HORTIAGRO F.C",
          "gols_mandante": null,
          "gols_visitante": null,
          "campo": "ARENA PRIME SOCIETY",
          "data_hora": "13/05/2026 21:30"
        }
      ]
    },
    {
      "nome": "Rodada 10 de 10",
      "jogos": [
        {
          "mandante": "E.C RONDOFRIO",
          "visitante": "R.C SPORTS",
          "gols_mandante": 4,
          "gols_visitante": 2,
          "campo": "ARENA PRIME SOCIETY",
          "data_hora": "29/04/2026 20:30"
        },
        {
          "mandante": "GG PINTURAS/SANTA MARIA",
          "visitante": "SHALON FC",
          "gols_mandante": 3,
          "gols_visitante": 5,
          "campo": "ARENA PRIME SOCIETY",
          "data_hora": "29/04/2026 21:30"
        },
        {
          "mandante": "SEDE DO GORDO",
          "visitante": "MECANICA CASTELI / HORTIAGRO F.C",
          "gols_mandante": 2,
          "gols_visitante": 3,
          "campo": "GUATAMBU SOCIETY",
          "data_hora": "30/04/2026 20:00"
        },
        {
          "mandante": "LJS/P2",
          "visitante": "BOLEIROS/MDM CONSTRUÇÕES E PINTURAS",
          "gols_mandante": 5,
          "gols_visitante": 5,
          "campo": "GUATAMBU SOCIETY",
          "data_hora": "30/04/2026 21:00"
        },
        {
          "mandante": "LJS/P2",
          "visitante": "BOLEIROS/MDM CONSTRUÇÕES E PINTURAS",
          "gols_mandante": 7,
          "gols_visitante": 6,
          "campo": "Pênalti",
          "data_hora": "30/04/2026 21:30"
        },
        {
          "mandante": "SHALON FC",
          "visitante": "LJS/P2",
          "gols_mandante": null,
          "gols_visitante": null,
          "campo": "ARENA PRIME SOCIETY",
          "data_hora": "13/05/2026 20:30"
        },
        {
          "mandante": "E.C RONDOFRIO",
          "visitante": "MECANICA CASTELI / HORTIAGRO F.C",
          "gols_mandante": null,
          "gols_visitante": null,
          "campo": "ARENA PRIME SOCIETY",
          "data_hora": "13/05/2026 21:30"
        }
      ]
    },
    {
      "nome": "Rodada 10 de 10",
      "jogos": [
        {
          "mandante": "E.C RONDOFRIO",
          "visitante": "R.C SPORTS",
          "gols_mandante": 4,
          "gols_visitante": 2,
          "campo": "ARENA PRIME SOCIETY",
          "data_hora": "29/04/2026 20:30"
        },
        {
          "mandante": "GG PINTURAS/SANTA MARIA",
          "visitante": "SHALON FC",
          "gols_mandante": 3,
          "gols_visitante": 5,
          "campo": "ARENA PRIME SOCIETY",
          "data_hora": "29/04/2026 21:30"
        },
        {
          "mandante": "SEDE DO GORDO",
          "visitante": "MECANICA CASTELI / HORTIAGRO F.C",
          "gols_mandante": 2,
          "gols_visitante": 3,
          "campo": "GUATAMBU SOCIETY",
          "data_hora": "30/04/2026 20:00"
        },
        {
          "mandante": "LJS/P2",
          "visitante": "BOLEIROS/MDM CONSTRUÇÕES E PINTURAS",
          "gols_mandante": 5,
          "gols_visitante": 5,
          "campo": "GUATAMBU SOCIETY",
          "data_hora": "30/04/2026 21:00"
        },
        {
          "mandante": "LJS/P2",
          "visitante": "BOLEIROS/MDM CONSTRUÇÕES E PINTURAS",
          "gols_mandante": 7,
          "gols_visitante": 6,
          "campo": "Pênalti",
          "data_hora": "30/04/2026 21:30"
        },
        {
          "mandante": "SHALON FC",
          "visitante": "LJS/P2",
          "gols_mandante": null,
          "gols_visitante": null,
          "campo": "ARENA PRIME SOCIETY",
          "data_hora": "13/05/2026 20:30"
        },
        {
          "mandante": "E.C RONDOFRIO",
          "visitante": "MECANICA CASTELI / HORTIAGRO F.C",
          "gols_mandante": null,
          "gols_visitante": null,
          "campo": "ARENA PRIME SOCIETY",
          "data_hora": "13/05/2026 21:30"
        }
      ]
    },
    {
      "nome": "Rodada 10 de 10",
      "jogos": [
        {
          "mandante": "E.C RONDOFRIO",
          "visitante": "R.C SPORTS",
          "gols_mandante": 4,
          "gols_visitante": 2,
          "campo": "ARENA PRIME SOCIETY",
          "data_hora": "29/04/2026 20:30"
        },
        {
          "mandante": "GG PINTURAS/SANTA MARIA",
          "visitante": "SHALON FC",
          "gols_mandante": 3,
          "gols_visitante": 5,
          "campo": "ARENA PRIME SOCIETY",
          "data_hora": "29/04/2026 21:30"
        },
        {
          "mandante": "SEDE DO GORDO",
          "visitante": "MECANICA CASTELI / HORTIAGRO F.C",
          "gols_mandante": 2,
          "gols_visitante": 3,
          "campo": "GUATAMBU SOCIETY",
          "data_hora": "30/04/2026 20:00"
        },
        {
          "mandante": "LJS/P2",
          "visitante": "BOLEIROS/MDM CONSTRUÇÕES E PINTURAS",
          "gols_mandante": 5,
          "gols_visitante": 5,
          "campo": "GUATAMBU SOCIETY",
          "data_hora": "30/04/2026 21:00"
        },
        {
          "mandante": "LJS/P2",
          "visitante": "BOLEIROS/MDM CONSTRUÇÕES E PINTURAS",
          "gols_mandante": 7,
          "gols_visitante": 6,
          "campo": "Pênalti",
          "data_hora": "30/04/2026 21:30"
        },
        {
          "mandante": "SHALON FC",
          "visitante": "LJS/P2",
          "gols_mandante": null,
          "gols_visitante": null,
          "campo": "ARENA PRIME SOCIETY",
          "data_hora": "13/05/2026 20:30"
        },
        {
          "mandante": "E.C RONDOFRIO",
          "visitante": "MECANICA CASTELI / HORTIAGRO F.C",
          "gols_mandante": null,
          "gols_visitante": null,
          "campo": "ARENA PRIME SOCIETY",
          "data_hora": "13/05/2026 21:30"
        }
      ]
    },
    {
      "nome": "Rodada 10 de 10",
      "jogos": [
        {
          "mandante": "E.C RONDOFRIO",
          "visitante": "R.C SPORTS",
          "gols_mandante": 4,
          "gols_visitante": 2,
          "campo": "ARENA PRIME SOCIETY",
          "data_hora": "29/04/2026 20:30"
        },
        {
          "mandante": "GG PINTURAS/SANTA MARIA",
          "visitante": "SHALON FC",
          "gols_mandante": 3,
          "gols_visitante": 5,
          "campo": "ARENA PRIME SOCIETY",
          "data_hora": "29/04/2026 21:30"
        },
        {
          "mandante": "SEDE DO GORDO",
          "visitante": "MECANICA CASTELI / HORTIAGRO F.C",
          "gols_mandante": 2,
          "gols_visitante": 3,
          "campo": "GUATAMBU SOCIETY",
          "data_hora": "30/04/2026 20:00"
        },
        {
          "mandante": "LJS/P2",
          "visitante": "BOLEIROS/MDM CONSTRUÇÕES E PINTURAS",
          "gols_mandante": 5,
          "gols_visitante": 5,
          "campo": "GUATAMBU SOCIETY",
          "data_hora": "30/04/2026 21:00"
        },
        {
          "mandante": "LJS/P2",
          "visitante": "BOLEIROS/MDM CONSTRUÇÕES E PINTURAS",
          "gols_mandante": 7,
          "gols_visitante": 6,
          "campo": "Pênalti",
          "data_hora": "30/04/2026 21:30"
        },
        {
          "mandante": "SHALON FC",
          "visitante": "LJS/P2",
          "gols_mandante": null,
          "gols_visitante": null,
          "campo": "ARENA PRIME SOCIETY",
          "data_hora": "13/05/2026 20:30"
        },
        {
          "mandante": "E.C RONDOFRIO",
          "visitante": "MECANICA CASTELI / HORTIAGRO F.C",
          "gols_mandante": null,
          "gols_visitante": null,
          "campo": "ARENA PRIME SOCIETY",
          "data_hora": "13/05/2026 21:30"
        }
      ]
    },
    {
      "nome": "Rodada 10 de 10",
      "jogos": [
        {
          "mandante": "E.C RONDOFRIO",
          "visitante": "R.C SPORTS",
          "gols_mandante": 4,
          "gols_visitante": 2,
          "campo": "ARENA PRIME SOCIETY",
          "data_hora": "29/04/2026 20:30"
        },
        {
          "mandante": "GG PINTURAS/SANTA MARIA",
          "visitante": "SHALON FC",
          "gols_mandante": 3,
          "gols_visitante": 5,
          "campo": "ARENA PRIME SOCIETY",
          "data_hora": "29/04/2026 21:30"
        },
        {
          "mandante": "SEDE DO GORDO",
          "visitante": "MECANICA CASTELI / HORTIAGRO F.C",
          "gols_mandante": 2,
          "gols_visitante": 3,
          "campo": "GUATAMBU SOCIETY",
          "data_hora": "30/04/2026 20:00"
        },
        {
          "mandante": "LJS/P2",
          "visitante": "BOLEIROS/MDM CONSTRUÇÕES E PINTURAS",
          "gols_mandante": 5,
          "gols_visitante": 5,
          "campo": "GUATAMBU SOCIETY",
          "data_hora": "30/04/2026 21:00"
        },
        {
          "mandante": "LJS/P2",
          "visitante": "BOLEIROS/MDM CONSTRUÇÕES E PINTURAS",
          "gols_mandante": 7,
          "gols_visitante": 6,
          "campo": "Pênalti",
          "data_hora": "30/04/2026 21:30"
        },
        {
          "mandante": "SHALON FC",
          "visitante": "LJS/P2",
          "gols_mandante": null,
          "gols_visitante": null,
          "campo": "ARENA PRIME SOCIETY",
          "data_hora": "13/05/2026 20:30"
        },
        {
          "mandante": "E.C RONDOFRIO",
          "visitante": "MECANICA CASTELI / HORTIAGRO F.C",
          "gols_mandante": null,
          "gols_visitante": null,
          "campo": "ARENA PRIME SOCIETY",
          "data_hora": "13/05/2026 21:30"
        }
      ]
    },
    {
      "nome": "Rodada 10 de 10",
      "jogos": [
        {
          "mandante": "E.C RONDOFRIO",
          "visitante": "R.C SPORTS",
          "gols_mandante": 4,
          "gols_visitante": 2,
          "campo": "ARENA PRIME SOCIETY",
          "data_hora": "29/04/2026 20:30"
        },
        {
          "mandante": "GG PINTURAS/SANTA MARIA",
          "visitante": "SHALON FC",
          "gols_mandante": 3,
          "gols_visitante": 5,
          "campo": "ARENA PRIME SOCIETY",
          "data_hora": "29/04/2026 21:30"
        },
        {
          "mandante": "SEDE DO GORDO",
          "visitante": "MECANICA CASTELI / HORTIAGRO F.C",
          "gols_mandante": 2,
          "gols_visitante": 3,
          "campo": "GUATAMBU SOCIETY",
          "data_hora": "30/04/2026 20:00"
        },
        {
          "mandante": "LJS/P2",
          "visitante": "BOLEIROS/MDM CONSTRUÇÕES E PINTURAS",
          "gols_mandante": 5,
          "gols_visitante": 5,
          "campo": "GUATAMBU SOCIETY",
          "data_hora": "30/04/2026 21:00"
        },
        {
          "mandante": "LJS/P2",
          "visitante": "BOLEIROS/MDM CONSTRUÇÕES E PINTURAS",
          "gols_mandante": 7,
          "gols_visitante": 6,
          "campo": "Pênalti",
          "data_hora": "30/04/2026 21:30"
        },
        {
          "mandante": "SHALON FC",
          "visitante": "LJS/P2",
          "gols_mandante": null,
          "gols_visitante": null,
          "campo": "ARENA PRIME SOCIETY",
          "data_hora": "13/05/2026 20:30"
        },
        {
          "mandante": "E.C RONDOFRIO",
          "visitante": "MECANICA CASTELI / HORTIAGRO F.C",
          "gols_mandante": null,
          "gols_visitante": null,
          "campo": "ARENA PRIME SOCIETY",
          "data_hora": "13/05/2026 21:30"
        }
      ]
    }
  ]
}